parakh1/__init__.py
parakh1-0.1.dist-info/METADATA
parakh1-0.1.dist-info/WHEEL
parakh1-0.1.dist-info/top_level.txt
parakh1-0.1.dist-info/RECORD
