Metadata-Version: 2.1
Name: parakh1
Version: 0.1
Summary: add the number
Home-page: UNKNOWN
Author: parakhsg
Author-email: parakh.tayal@sganalytics.com
License: MIT
Platform: UNKNOWN
